{"P8": {"labels": ["enhancement"], "postTitle": "This i", "postUrl": "post/This%20i.html", "createdDate": "2024-12-31", "dateLabelColor": "#bc4c00"}, "P4": {"labels": ["documentation"], "postTitle": "\u6211\u7684\u5934\u50cf", "postUrl": "post/wo-de-tou-xiang.html", "createdDate": "2024-12-09", "dateLabelColor": "#bc4c00"}, "P1": {"labels": ["documentation"], "postTitle": "\u56db\u5934\u65e0\u5fe7\u7684\u535a\u5ba2", "postUrl": "post/si-tou-wu-you-de-bo-ke.html", "createdDate": "2024-12-09", "dateLabelColor": "#bc4c00"}, "labelColorDict": {"bug": "#d73a4a", "documentation": "#0075ca", "duplicate": "#cfd3d7", "enhancement": "#a2eeef", "good first issue": "#7057ff", "help wanted": "#008672", "invalid": "#e4e669", "question": "#d876e3", "wontfix": "#ffffff"}}